mosaic_benchmark/__init__.py
mosaic_benchmark/edge_generation_helper.py
mosaic_benchmark/edge_generator.py
mosaic_benchmark/modular_link_stream.py
mosaic_benchmark/mosaic_community.py
mosaic_benchmark/random_scenario_helper.py
mosaic_benchmark/scenario_checker.py
mosaic_benchmark/snapshot_scenario_helper.py
mosaic_benchmark/visualisation_helper.py
mosaic_benchmark-0.2.2.dist-info/METADATA
mosaic_benchmark-0.2.2.dist-info/WHEEL
mosaic_benchmark-0.2.2.dist-info/RECORD
