Metadata-Version: 2.1
Name: mosaic-benchmark
Version: 0.2.2
Summary: A package to create modular link streams used for testing dynamic community detection algoritms
Home-page: https://yasasgari.github.io/Mosaic-benchmark/
License: MIT
Keywords: Temporal networks,community detection,Graphs,Complex networks
Author: Yasaman Asgari
Author-email: yasasgary@gmail.com
Requires-Python: >=3.8,<4.0
Classifier: License :: OSI Approved :: MIT License
Classifier: Programming Language :: Python :: 3
Classifier: Programming Language :: Python :: 3.8
Classifier: Programming Language :: Python :: 3.9
Classifier: Programming Language :: Python :: 3.10
Classifier: Programming Language :: Python :: 3.11
Project-URL: Repository, https://github.com/YasAsgari/Mosaic-benchmark
